setup.cfg
setup.py
pyndroid/pyandroid.py
pyndroid.egg-info/PKG-INFO
pyndroid.egg-info/SOURCES.txt
pyndroid.egg-info/dependency_links.txt
pyndroid.egg-info/not-zip-safe
pyndroid.egg-info/top_level.txt
pyndroid/resources/AndroidManifest.xml
pyndroid/resources/java/DatabaseHelper.java
pyndroid/resources/java/HistoryActivity.java
pyndroid/resources/java/HistoryAdapter.java
pyndroid/resources/java/MainActivity.java
pyndroid/resources/java/PrintHistory.java
pyndroid/resources/java/Printer.java
pyndroid/resources/java/PrinterAdapter.java
pyndroid/resources/java/PrintersActivity.java
pyndroid/resources/java/RegisterActivity.java
pyndroid/resources/java/User.java
pyndroid/resources/layout/activity_history.xml
pyndroid/resources/layout/activity_main.xml
pyndroid/resources/layout/activity_printers.xml
pyndroid/resources/layout/activity_register.xml
pyndroid/resources/layout/item_history.xml
pyndroid/resources/layout/item_printer.xml