Metadata-Version: 2.1
Name: pyndroid
Version: 1.0
Summary: Android developing
Author-email: a.s.ulmasov@yandex.ru
